fuzzy_core-0.1.1.dist-info/METADATA
fuzzy_core-0.1.1.dist-info/WHEEL
fuzzy_core/__init__.py
fuzzy_core/fuzzy_core.cpython-311-x86_64-linux-gnu.so
fuzzy_core-0.1.1.dist-info/RECORD
