Metadata-Version: 2.4
Name: fuzzy-core
Version: 0.1.1
Classifier: Development Status :: 3 - Alpha
Classifier: Intended Audience :: Developers
Classifier: Topic :: Software Development :: Libraries
Classifier: Topic :: Text Processing
Classifier: License :: OSI Approved :: MIT License
Classifier: Programming Language :: Python :: 3
Classifier: Programming Language :: Python :: 3.9
Classifier: Programming Language :: Python :: 3.10
Classifier: Programming Language :: Python :: 3.11
Summary: Spec-first fuzzy string similarity core (Rust + Python)
Keywords: fuzzy,string-matching,similarity,levenshtein,rust
Author: Heritechie
License: MIT
Requires-Python: >=3.8
Project-URL: Homepage, https://github.com/heritechie/fuzzy-core
Project-URL: Repository, https://github.com/heritechie/fuzzy-core
Project-URL: Issues, https://github.com/heritechie/fuzzy-core/issues
